[{"schid": "070161460042002", "name": "Bert H Fulton School", "distid": "070161460040000", "dist": "CCSD 146", "city": "Tinley Park", "county": "Cook", "type": "ELEMENTARY", "lowinc2004": "17.1", "percmin2004": "11.7", "enroll2004": "375", "enrolldist2004": "2420", "grades2004": "PK K 1 2", "sel2004elem": "No", "elemcomp2004": "None", "sel2004hs": "No", "hscomp2004": "None", "zelemscore2004": "None", "avgelem2004": "None", "stdvelem2004": "None", "zhsscore2004": "None", "avghs2004": "None", "stdvhs2004": "None", "lowinc2005": "21.5", "percmin2005": "12.3", "enroll2005": "381", "enrolldist2005": "2434", "grades2005": "PK K 1 2", "sel2005elem": "No", "elemcomp2005": "None", "sel2005hs": "No", "hscomp2005": "None", "zelemscore2005": "None", "avgelem2005": "None", "stdvelem2005": "None", "zhsscore2005": "None", "avghs2005": "None", "stdvhs2005": "None", "lowinc2006": "18.1", "percmin2006": "13.5", "enroll2006": "370", "enrolldist2006": "2407", "grades2006": "PK K 1 2", "sel2006elem": "No", "elemcomp2006": "None", "sel2006hs": "No", "hscomp2006": "None", "zelemscore2006": "None", "avgelem2006": "None", "stdvelem2006": "None", "zhsscore2006": "None", "avghs2006": "None", "stdvhs2006": "None", "lowinc2007": "20.3", "percmin2007": "10.7", "enroll2007": "345", "enrolldist2007": "2401", "grades2007": "PK K 1 2", "sel2007elem": "No", "elemcomp2007": "None", "sel2007hs": "No", "hscomp2007": "None", "zelemscore2007": "None", "avgelem2007": "None", "stdvelem2007": "None", "zhsscore2007": "None", "avghs2007": "None", "stdvhs2007": "None", "lowinc2008": "20.2", "percmin2008": "17.2", "enroll2008": "297", "enrolldist2008": "2414", "grades2008": "PK K 1 2", "sel2008elem": "No", "elemcomp2008": "None", "sel2008hs": "No", "hscomp2008": "None", "zelemscore2008": "None", "avgelem2008": "None", "stdvelem2008": "None", "zhsscore2008": "None", "avghs2008": "None", "stdvhs2008": "None", "lowinc2009": "None", "percmin2009": "None", "enroll2009": "None", "enrolldist2009": "None", "grades2009": "None", "sel2009elem": "No", "elemcomp2009": "None", "sel2009hs": "No", "hscomp2009": "None", "zelemscore2009": "None", "avgelem2009": "None", "stdvelem2009": "None", "zhsscore2009": "None", "avghs2009": "None", "stdvhs2009": "None", "lowinc2010": "32.5", "percmin2010": "20.1", "enroll2010": "551", "enrolldist2010": "2333", "grades2010": "PK K 1 2 3 4 5", "sel2010elem": "Yes", "elemcomp2010": "84.5", "sel2010hs": "No", "hscomp2010": "None", "zelemscore2010": "-0.24", "avgelem2010": "85.7", "stdvelem2010": "5.26", "zhsscore2010": "None", "avghs2010": "None", "stdvhs2010": "None", "lowinc2011": "34.6", "percmin2011": "24.0", "enroll2011": "537", "enrolldist2011": "2351", "grades2011": "PK K 1 2 3 4 5", "sel2011elem": "Yes", "elemcomp2011": "84.7", "sel2011hs": "No", "hscomp2011": "None", "zelemscore2011": "-0.52", "avgelem2011": "87.3", "stdvelem2011": "4.91", "zhsscore2011": "None", "avghs2011": "None", "stdvhs2011": "None", "lowinc2012": "34.5", "percmin2012": "25.0", "enroll2012": "585", "enrolldist2012": "2408", "grades2012": "PK K 1 2 3 4 5", "sel2012elem": "Yes", "elemcomp2012": "90.0", "sel2012hs": "No", "hscomp2012": "None", "zelemscore2012": "0.55", "avgelem2012": "87.4", "stdvelem2012": "4.72", "zhsscore2012": "None", "avghs2012": "None", "stdvhs2012": "None", "lowinc2013": "31.8", "percmin2013": "24.9", "enroll2013": "579", "enrolldist2013": "2358", "grades2013": "PK K 1 2 3 4 5", "sel2013elem": "Yes", "elemcomp2013": "71.7", "sel2013hs": "No", "hscomp2013": "None", "zelemscore2013": "0.64", "avgelem2013": "66.1", "stdvelem2013": "8.82", "zhsscore2013": "None", "avghs2013": "None", "stdvhs2013": "None", "lowinc2014": "40.6", "percmin2014": "25.6", "enroll2014": "614", "enrolldist2014": "2391", "grades2014": "PK K 1 2 3 4 5", "sel2014elem": "Yes", "elemcomp2014": "72.0", "sel2014hs": "No", "hscomp2014": "None", "zelemscore2014": "1.19", "avgelem2014": "60.5", "stdvelem2014": "9.63", "zhsscore2014": "None", "avghs2014": "None", "stdvhs2014": "None"}, {"schid": "070161460042005", "name": "Walter F Fierke Ed Center", "distid": "070161460040000", "dist": "CCSD 146", "city": "Oak Forest", "county": "Cook", "type": "ELEMENTARY", "lowinc2004": "10.1", "percmin2004": "12.4", "enroll2004": "298", "enrolldist2004": "2420", "grades2004": "K 1 2 3 4 5", "sel2004elem": "Yes", "elemcomp2004": "82.6", "sel2004hs": "No", "hscomp2004": "None", "zelemscore2004": "0.76", "avgelem2004": "76.7", "stdvelem2004": "7.74", "zhsscore2004": "None", "avghs2004": "None", "stdvhs2004": "None", "lowinc2005": "13.4", "percmin2005": "14.3", "enroll2005": "321", "enrolldist2005": "2434", "grades2005": "K 1 2 3 4 5", "sel2005elem": "Yes", "elemcomp2005": "78.7", "sel2005hs": "No", "hscomp2005": "None", "zelemscore2005": "-0.31", "avgelem2005": "80.8", "stdvelem2005": "6.96", "zhsscore2005": "None", "avghs2005": "None", "stdvhs2005": "None", "lowinc2006": "17.0", "percmin2006": "17.6", "enroll2006": "335", "enrolldist2006": "2407", "grades2006": "K 1 2 3 4 5", "sel2006elem": "Yes", "elemcomp2006": "87.7", "sel2006hs": "No", "hscomp2006": "None", "zelemscore2006": "0.19", "avgelem2006": "86.8", "stdvelem2006": "4.89", "zhsscore2006": "None", "avghs2006": "None", "stdvhs2006": "None", "lowinc2007": "12.4", "percmin2007": "18.7", "enroll2007": "348", "enrolldist2007": "2401", "grades2007": "K 1 2 3 4 5", "sel2007elem": "Yes", "elemcomp2007": "91.0", "sel2007hs": "No", "hscomp2007": "None", "zelemscore2007": "0.66", "avgelem2007": "87.6", "stdvelem2007": "5.24", "zhsscore2007": "None", "avghs2007": "None", "stdvhs2007": "None", "lowinc2008": "17.8", "percmin2008": "20.8", "enroll2008": "360", "enrolldist2008": "2414", "grades2008": "PK K 1 2 3 4 5", "sel2008elem": "Yes", "elemcomp2008": "87.9", "sel2008hs": "No", "hscomp2008": "None", "zelemscore2008": "-0.06", "avgelem2008": "88.2", "stdvelem2008": "4.59", "zhsscore2008": "None", "avghs2008": "None", "stdvhs2008": "None", "lowinc2009": "18.3", "percmin2009": "18.6", "enroll2009": "366", "enrolldist2009": "2406", "grades2009": "PK K 1 2 3 4 5", "sel2009elem": "Yes", "elemcomp2009": "87.3", "sel2009hs": "No", "hscomp2009": "None", "zelemscore2009": "-0.45", "avgelem2009": "89.2", "stdvelem2009": "4.26", "zhsscore2009": "None", "avghs2009": "None", "stdvhs2009": "None", "lowinc2010": "22.1", "percmin2010": "18.3", "enroll2010": "339", "enrolldist2010": "2333", "grades2010": "PK K 1 2 3 4 5", "sel2010elem": "Yes", "elemcomp2010": "88.5", "sel2010hs": "No", "hscomp2010": "None", "zelemscore2010": "0.09", "avgelem2010": "88.1", "stdvelem2010": "4.84", "zhsscore2010": "None", "avghs2010": "None", "stdvhs2010": "None", "lowinc2011": "23.4", "percmin2011": "18.6", "enroll2011": "312", "enrolldist2011": "2351", "grades2011": "PK K 1 2 3 4 5", "sel2011elem": "Yes", "elemcomp2011": "93.0", "sel2011hs": "No", "hscomp2011": "None", "zelemscore2011": "0.82", "avgelem2011": "89.2", "stdvelem2011": "4.66", "zhsscore2011": "None", "avghs2011": "None", "stdvhs2011": "None", "lowinc2012": "21.2", "percmin2012": "18.2", "enroll2012": "297", "enrolldist2012": "2408", "grades2012": "PK K 1 2 3 4 5", "sel2012elem": "Yes", "elemcomp2012": "94.0", "sel2012hs": "No", "hscomp2012": "None", "zelemscore2012": "1.13", "avgelem2012": "89.8", "stdvelem2012": "3.67", "zhsscore2012": "None", "avghs2012": "None", "stdvhs2012": "None", "lowinc2013": "20.2", "percmin2013": "17.9", "enroll2013": "307", "enrolldist2013": "2358", "grades2013": "PK K 1 2 3 4 5", "sel2013elem": "Yes", "elemcomp2013": "72.7", "sel2013hs": "No", "hscomp2013": "None", "zelemscore2013": "0.18", "avgelem2013": "71.2", "stdvelem2013": "8.24", "zhsscore2013": "None", "avghs2013": "None", "stdvhs2013": "None", "lowinc2014": "29.3", "percmin2014": "20.2", "enroll2014": "321", "enrolldist2014": "2391", "grades2014": "PK K 1 2 3 4 5", "sel2014elem": "Yes", "elemcomp2014": "73.0", "sel2014hs": "No", "hscomp2014": "None", "zelemscore2014": "0.08", "avgelem2014": "72.3", "stdvelem2014": "8.44", "zhsscore2014": "None", "avghs2014": "None", "stdvhs2014": "None"}, {"schid": "070161460042006", "name": "Arnold W Kruse Ed Center", "distid": "070161460040000", "dist": "CCSD 146", "city": "Orland Park", "county": "Cook", "type": "ELEMENTARY", "lowinc2004": "12.1", "percmin2004": "13.7", "enroll2004": "313", "enrolldist2004": "2420", "grades2004": "K 1 2 3 4 5", "sel2004elem": "Yes", "elemcomp2004": "81.6", "sel2004hs": "No", "hscomp2004": "None", "zelemscore2004": "0.63", "avgelem2004": "76.7", "stdvelem2004": "7.74", "zhsscore2004": "None", "avghs2004": "None", "stdvhs2004": "None", "lowinc2005": "16.0", "percmin2005": "13.1", "enroll2005": "313", "enrolldist2005": "2434", "grades2005": "K 1 2 3 4 5", "sel2005elem": "Yes", "elemcomp2005": "79.2", "sel2005hs": "No", "hscomp2005": "None", "zelemscore2005": "-0.24", "avgelem2005": "80.8", "stdvelem2005": "6.96", "zhsscore2005": "None", "avghs2005": "None", "stdvhs2005": "None", "lowinc2006": "17.4", "percmin2006": "16.5", "enroll2006": "310", "enrolldist2006": "2407", "grades2006": "K 1 2 3 4 5", "sel2006elem": "Yes", "elemcomp2006": "86.0", "sel2006hs": "No", "hscomp2006": "None", "zelemscore2006": "-0.16", "avgelem2006": "86.8", "stdvelem2006": "4.89", "zhsscore2006": "None", "avghs2006": "None", "stdvhs2006": "None", "lowinc2007": "16.2", "percmin2007": "13.5", "enroll2007": "303", "enrolldist2007": "2401", "grades2007": "K 1 2 3 4 5", "sel2007elem": "Yes", "elemcomp2007": "85.7", "sel2007hs": "No", "hscomp2007": "None", "zelemscore2007": "-0.35", "avgelem2007": "87.6", "stdvelem2007": "5.24", "zhsscore2007": "None", "avghs2007": "None", "stdvhs2007": "None", "lowinc2008": "18.4", "percmin2008": "11.8", "enroll2008": "321", "enrolldist2008": "2414", "grades2008": "PK K 1 2 3 4 5", "sel2008elem": "Yes", "elemcomp2008": "86.4", "sel2008hs": "No", "hscomp2008": "None", "zelemscore2008": "-0.39", "avgelem2008": "88.2", "stdvelem2008": "4.59", "zhsscore2008": "None", "avghs2008": "None", "stdvhs2008": "None", "lowinc2009": "19.1", "percmin2009": "14.6", "enroll2009": "383", "enrolldist2009": "2406", "grades2009": "PK K 1 2 3 4 5", "sel2009elem": "Yes", "elemcomp2009": "93.0", "sel2009hs": "No", "hscomp2009": "None", "zelemscore2009": "0.89", "avgelem2009": "89.2", "stdvelem2009": "4.26", "zhsscore2009": "None", "avghs2009": "None", "stdvhs2009": "None", "lowinc2010": "23.5", "percmin2010": "17.9", "enroll2010": "336", "enrolldist2010": "2333", "grades2010": "PK K 1 2 3 4 5", "sel2010elem": "Yes", "elemcomp2010": "89.4", "sel2010hs": "No", "hscomp2010": "None", "zelemscore2010": "0.28", "avgelem2010": "88.1", "stdvelem2010": "4.84", "zhsscore2010": "None", "avghs2010": "None", "stdvhs2010": "None", "lowinc2011": "27.0", "percmin2011": "21.7", "enroll2011": "345", "enrolldist2011": "2351", "grades2011": "PK K 1 2 3 4 5", "sel2011elem": "Yes", "elemcomp2011": "91.5", "sel2011hs": "No", "hscomp2011": "None", "zelemscore2011": "0.50", "avgelem2011": "89.2", "stdvelem2011": "4.66", "zhsscore2011": "None", "avghs2011": "None", "stdvhs2011": "None", "lowinc2012": "28.6", "percmin2012": "20.1", "enroll2012": "353", "enrolldist2012": "2408", "grades2012": "PK K 1 2 3 4 5", "sel2012elem": "Yes", "elemcomp2012": "90.6", "sel2012hs": "No", "hscomp2012": "None", "zelemscore2012": "0.21", "avgelem2012": "89.8", "stdvelem2012": "3.67", "zhsscore2012": "None", "avghs2012": "None", "stdvhs2012": "None", "lowinc2013": "32.3", "percmin2013": "22.7", "enroll2013": "322", "enrolldist2013": "2358", "grades2013": "PK K 1 2 3 4 5", "sel2013elem": "Yes", "elemcomp2013": "75.1", "sel2013hs": "No", "hscomp2013": "None", "zelemscore2013": "1.02", "avgelem2013": "66.1", "stdvelem2013": "8.82", "zhsscore2013": "None", "avghs2013": "None", "stdvhs2013": "None", "lowinc2014": "43.2", "percmin2014": "25.3", "enroll2014": "340", "enrolldist2014": "2391", "grades2014": "PK K 1 2 3 4 5", "sel2014elem": "Yes", "elemcomp2014": "75.0", "sel2014hs": "No", "hscomp2014": "None", "zelemscore2014": "1.51", "avgelem2014": "60.5", "stdvelem2014": "9.63", "zhsscore2014": "None", "avghs2014": "None", "stdvhs2014": "None"}, {"schid": "070161460042003", "name": "Memorial Elem School", "distid": "070161460040000", "dist": "CCSD 146", "city": "Tinley Park", "county": "Cook", "type": "ELEMENTARY", "lowinc2004": "15.2", "percmin2004": "14.9", "enroll2004": "355", "enrolldist2004": "2420", "grades2004": "K 1 2 3 4 5", "sel2004elem": "Yes", "elemcomp2004": "80.7", "sel2004hs": "No", "hscomp2004": "None", "zelemscore2004": "0.52", "avgelem2004": "76.7", "stdvelem2004": "7.74", "zhsscore2004": "None", "avghs2004": "None", "stdvhs2004": "None", "lowinc2005": "18.1", "percmin2005": "16.0", "enroll2005": "349", "enrolldist2005": "2434", "grades2005": "K 1 2 3 4 5", "sel2005elem": "Yes", "elemcomp2005": "83.1", "sel2005hs": "No", "hscomp2005": "None", "zelemscore2005": "0.32", "avgelem2005": "80.8", "stdvelem2005": "6.96", "zhsscore2005": "None", "avghs2005": "None", "stdvhs2005": "None", "lowinc2006": "19.2", "percmin2006": "17.7", "enroll2006": "339", "enrolldist2006": "2407", "grades2006": "K 1 2 3 4 5", "sel2006elem": "Yes", "elemcomp2006": "91.5", "sel2006hs": "No", "hscomp2006": "None", "zelemscore2006": "0.97", "avgelem2006": "86.8", "stdvelem2006": "4.89", "zhsscore2006": "None", "avghs2006": "None", "stdvhs2006": "None", "lowinc2007": "22.3", "percmin2007": "21.0", "enroll2007": "314", "enrolldist2007": "2401", "grades2007": "K 1 2 3 4 5", "sel2007elem": "Yes", "elemcomp2007": "87.7", "sel2007hs": "No", "hscomp2007": "None", "zelemscore2007": "0.45", "avgelem2007": "85.2", "stdvelem2007": "5.48", "zhsscore2007": "None", "avghs2007": "None", "stdvhs2007": "None", "lowinc2008": "23.2", "percmin2008": "19.8", "enroll2008": "349", "enrolldist2008": "2414", "grades2008": "PK K 1 2 3 4 5", "sel2008elem": "Yes", "elemcomp2008": "88.6", "sel2008hs": "No", "hscomp2008": "None", "zelemscore2008": "0.47", "avgelem2008": "86.1", "stdvelem2008": "5.37", "zhsscore2008": "None", "avghs2008": "None", "stdvhs2008": "None", "lowinc2009": "26.7", "percmin2009": "21.8", "enroll2009": "435", "enrolldist2009": "2406", "grades2009": "PK K 1 2 3 4 5", "sel2009elem": "Yes", "elemcomp2009": "86.2", "sel2009hs": "No", "hscomp2009": "None", "zelemscore2009": "-0.11", "avgelem2009": "86.8", "stdvelem2009": "5.14", "zhsscore2009": "None", "avghs2009": "None", "stdvhs2009": "None", "lowinc2010": "28.1", "percmin2010": "23.3", "enroll2010": "331", "enrolldist2010": "2333", "grades2010": "PK K 1 2 3 4 5", "sel2010elem": "Yes", "elemcomp2010": "88.9", "sel2010hs": "No", "hscomp2010": "None", "zelemscore2010": "0.17", "avgelem2010": "88.1", "stdvelem2010": "4.84", "zhsscore2010": "None", "avghs2010": "None", "stdvhs2010": "None", "lowinc2011": "34.3", "percmin2011": "26.7", "enroll2011": "341", "enrolldist2011": "2351", "grades2011": "PK K 1 2 3 4 5", "sel2011elem": "Yes", "elemcomp2011": "85.8", "sel2011hs": "No", "hscomp2011": "None", "zelemscore2011": "-0.30", "avgelem2011": "87.3", "stdvelem2011": "4.91", "zhsscore2011": "None", "avghs2011": "None", "stdvhs2011": "None", "lowinc2012": "35.0", "percmin2012": "30.8", "enroll2012": "334", "enrolldist2012": "2408", "grades2012": "PK K 1 2 3 4 5", "sel2012elem": "Yes", "elemcomp2012": "83.9", "sel2012hs": "No", "hscomp2012": "None", "zelemscore2012": "-0.74", "avgelem2012": "87.4", "stdvelem2012": "4.72", "zhsscore2012": "None", "avghs2012": "None", "stdvhs2012": "None", "lowinc2013": "34.4", "percmin2013": "25.0", "enroll2013": "372", "enrolldist2013": "2358", "grades2013": "PK K 1 2 3 4 5", "sel2013elem": "Yes", "elemcomp2013": "64.6", "sel2013hs": "No", "hscomp2013": "None", "zelemscore2013": "-0.17", "avgelem2013": "66.1", "stdvelem2013": "8.82", "zhsscore2013": "None", "avghs2013": "None", "stdvhs2013": "None", "lowinc2014": "40.1", "percmin2014": "26.2", "enroll2014": "359", "enrolldist2014": "2391", "grades2014": "PK K 1 2 3 4 5", "sel2014elem": "Yes", "elemcomp2014": "65.0", "sel2014hs": "No", "hscomp2014": "None", "zelemscore2014": "0.47", "avgelem2014": "60.5", "stdvelem2014": "9.63", "zhsscore2014": "None", "avghs2014": "None", "stdvhs2014": "None"}, {"schid": "070161460041001", "name": "Central Middle School", "distid": "070161460040000", "dist": "CCSD 146", "city": "Tinley Park", "county": "Cook", "type": "MIDDLE SCHL", "lowinc2004": "13.9", "percmin2004": "11.0", "enroll2004": "819", "enrolldist2004": "2420", "grades2004": "6 7 8", "sel2004elem": "Yes", "elemcomp2004": "75.2", "sel2004hs": "No", "hscomp2004": "None", "zelemscore2004": "-0.20", "avgelem2004": "76.7", "stdvelem2004": "7.74", "zhsscore2004": "None", "avghs2004": "None", "stdvhs2004": "None", "lowinc2005": "15.7", "percmin2005": "16.1", "enroll2005": "827", "enrolldist2005": "2434", "grades2005": "6 7 8", "sel2005elem": "Yes", "elemcomp2005": "79.2", "sel2005hs": "No", "hscomp2005": "None", "zelemscore2005": "-0.24", "avgelem2005": "80.8", "stdvelem2005": "6.96", "zhsscore2005": "None", "avghs2005": "None", "stdvhs2005": "None", "lowinc2006": "18.4", "percmin2006": "16.4", "enroll2006": "804", "enrolldist2006": "2407", "grades2006": "6 7 8", "sel2006elem": "Yes", "elemcomp2006": "83.2", "sel2006hs": "No", "hscomp2006": "None", "zelemscore2006": "-0.73", "avgelem2006": "86.8", "stdvelem2006": "4.89", "zhsscore2006": "None", "avghs2006": "None", "stdvhs2006": "None", "lowinc2007": "19.0", "percmin2007": "16.9", "enroll2007": "836", "enrolldist2007": "2401", "grades2007": "6 7 8", "sel2007elem": "Yes", "elemcomp2007": "84.1", "sel2007hs": "No", "hscomp2007": "None", "zelemscore2007": "-0.66", "avgelem2007": "87.6", "stdvelem2007": "5.24", "zhsscore2007": "None", "avghs2007": "None", "stdvhs2007": "None", "lowinc2008": "21.4", "percmin2008": "17.6", "enroll2008": "822", "enrolldist2008": "2414", "grades2008": "6 7 8", "sel2008elem": "Yes", "elemcomp2008": "84.2", "sel2008hs": "No", "hscomp2008": "None", "zelemscore2008": "-0.35", "avgelem2008": "86.1", "stdvelem2008": "5.37", "zhsscore2008": "None", "avghs2008": "None", "stdvhs2008": "None", "lowinc2009": "22.9", "percmin2009": "20.8", "enroll2009": "799", "enrolldist2009": "2406", "grades2009": "6 7 8", "sel2009elem": "Yes", "elemcomp2009": "83.7", "sel2009hs": "No", "hscomp2009": "None", "zelemscore2009": "-0.59", "avgelem2009": "86.8", "stdvelem2009": "5.14", "zhsscore2009": "None", "avghs2009": "None", "stdvhs2009": "None", "lowinc2010": "26.2", "percmin2010": "21.0", "enroll2010": "776", "enrolldist2010": "2333", "grades2010": "6 7 8", "sel2010elem": "Yes", "elemcomp2010": "83.5", "sel2010hs": "No", "hscomp2010": "None", "zelemscore2010": "-0.94", "avgelem2010": "88.1", "stdvelem2010": "4.84", "zhsscore2010": "None", "avghs2010": "None", "stdvhs2010": "None", "lowinc2011": "30.3", "percmin2011": "22.5", "enroll2011": "816", "enrolldist2011": "2351", "grades2011": "6 7 8", "sel2011elem": "Yes", "elemcomp2011": "85.2", "sel2011hs": "No", "hscomp2011": "None", "zelemscore2011": "-0.42", "avgelem2011": "87.3", "stdvelem2011": "4.91", "zhsscore2011": "None", "avghs2011": "None", "stdvhs2011": "None", "lowinc2012": "33.1", "percmin2012": "21.8", "enroll2012": "839", "enrolldist2012": "2408", "grades2012": "6 7 8", "sel2012elem": "Yes", "elemcomp2012": "85.4", "sel2012hs": "No", "hscomp2012": "None", "zelemscore2012": "-0.42", "avgelem2012": "87.4", "stdvelem2012": "4.72", "zhsscore2012": "None", "avghs2012": "None", "stdvhs2012": "None", "lowinc2013": "32.0", "percmin2013": "22.5", "enroll2013": "778", "enrolldist2013": "2358", "grades2013": "6 7 8", "sel2013elem": "Yes", "elemcomp2013": "62.5", "sel2013hs": "No", "hscomp2013": "None", "zelemscore2013": "-0.41", "avgelem2013": "66.1", "stdvelem2013": "8.82", "zhsscore2013": "None", "avghs2013": "None", "stdvhs2013": "None", "lowinc2014": "41.3", "percmin2014": "25.8", "enroll2014": "757", "enrolldist2014": "2391", "grades2014": "6 7 8", "sel2014elem": "Yes", "elemcomp2014": "63.0", "sel2014hs": "No", "hscomp2014": "None", "zelemscore2014": "0.26", "avgelem2014": "60.5", "stdvelem2014": "9.63", "zhsscore2014": "None", "avghs2014": "None", "stdvhs2014": "None"}]