[{"schid": "170530080260001", "name": "Prairie Central High School", "distid": "170530080260000", "dist": "Prairie Central CUSD 8", "city": "Fairbury", "county": "Livingston", "type": "HIGH SCHOOL", "lowinc2004": "19.5", "percmin2004": "3.0", "enroll2004": "605", "enrolldist2004": "1889", "grades2004": "9 10 11 12", "sel2004elem": "No", "elemcomp2004": "None", "sel2004hs": "Yes", "hscomp2004": "68.1", "zelemscore2004": "None", "avgelem2004": "None", "stdvelem2004": "None", "zhsscore2004": "1.26", "avghs2004": "56.6", "stdvhs2004": "9.10", "lowinc2005": "18.3", "percmin2005": "4.3", "enroll2005": "722", "enrolldist2005": "2307", "grades2005": "9 10 11 12", "sel2005elem": "No", "elemcomp2005": "None", "sel2005hs": "Yes", "hscomp2005": "59.1", "zelemscore2005": "None", "avgelem2005": "None", "stdvelem2005": "None", "zhsscore2005": "0.23", "avghs2005": "57.2", "stdvhs2005": "8.17", "lowinc2006": "26.2", "percmin2006": "4.9", "enroll2006": "699", "enrolldist2006": "2241", "grades2006": "9 10 11 12", "sel2006elem": "No", "elemcomp2006": "None", "sel2006hs": "Yes", "hscomp2006": "54.9", "zelemscore2006": "None", "avgelem2006": "None", "stdvelem2006": "None", "zhsscore2006": "0.28", "avghs2006": "51.6", "stdvhs2006": "11.62", "lowinc2007": "27.6", "percmin2007": "4.3", "enroll2007": "691", "enrolldist2007": "2199", "grades2007": "9 10 11 12", "sel2007elem": "No", "elemcomp2007": "None", "sel2007hs": "Yes", "hscomp2007": "59.4", "zelemscore2007": "None", "avgelem2007": "None", "stdvelem2007": "None", "zhsscore2007": "0.83", "avghs2007": "50.3", "stdvhs2007": "10.97", "lowinc2008": "33.4", "percmin2008": "5.3", "enroll2008": "659", "enrolldist2008": "2187", "grades2008": "9 10 11 12", "sel2008elem": "No", "elemcomp2008": "None", "sel2008hs": "Yes", "hscomp2008": "53.5", "zelemscore2008": "None", "avgelem2008": "None", "stdvelem2008": "None", "zhsscore2008": "0.24", "avghs2008": "50.9", "stdvhs2008": "10.81", "lowinc2009": "31.1", "percmin2009": "5.1", "enroll2009": "649", "enrolldist2009": "2178", "grades2009": "9 10 11 12", "sel2009elem": "No", "elemcomp2009": "None", "sel2009hs": "Yes", "hscomp2009": "53.9", "zelemscore2009": "None", "avgelem2009": "None", "stdvelem2009": "None", "zhsscore2009": "0.23", "avghs2009": "51.3", "stdvhs2009": "11.16", "lowinc2010": "33.8", "percmin2010": "5.3", "enroll2010": "618", "enrolldist2010": "2110", "grades2010": "9 10 11 12", "sel2010elem": "No", "elemcomp2010": "None", "sel2010hs": "Yes", "hscomp2010": "66.7", "zelemscore2010": "None", "avgelem2010": "None", "stdvelem2010": "None", "zhsscore2010": "1.47", "avghs2010": "52.4", "stdvhs2010": "9.71", "lowinc2011": "30.3", "percmin2011": "5.9", "enroll2011": "641", "enrolldist2011": "2154", "grades2011": "9 10 11 12", "sel2011elem": "No", "elemcomp2011": "None", "sel2011hs": "Yes", "hscomp2011": "59.1", "zelemscore2011": "None", "avgelem2011": "None", "stdvelem2011": "None", "zhsscore2011": "0.56", "avghs2011": "53.4", "stdvhs2011": "10.18", "lowinc2012": "31.1", "percmin2012": "6.8", "enroll2012": "614", "enrolldist2012": "2160", "grades2012": "9 10 11 12", "sel2012elem": "No", "elemcomp2012": "None", "sel2012hs": "Yes", "hscomp2012": "55.5", "zelemscore2012": "None", "avgelem2012": "None", "stdvelem2012": "None", "zhsscore2012": "0.14", "avghs2012": "54.0", "stdvhs2012": "10.53", "lowinc2013": "41.3", "percmin2013": "7.5", "enroll2013": "612", "enrolldist2013": "2117", "grades2013": "9 10 11 12", "sel2013elem": "No", "elemcomp2013": "None", "sel2013hs": "Yes", "hscomp2013": "58.9", "zelemscore2013": "None", "avgelem2013": "None", "stdvelem2013": "None", "zhsscore2013": "0.81", "avghs2013": "50.1", "stdvhs2013": "10.87", "lowinc2014": "39.0", "percmin2014": "7.5", "enroll2014": "623", "enrolldist2014": "2144", "grades2014": "9 10 11 12", "sel2014elem": "No", "elemcomp2014": "None", "sel2014hs": "Yes", "hscomp2014": "63.3", "zelemscore2014": "None", "avgelem2014": "None", "stdvelem2014": "None", "zhsscore2014": "1.12", "avghs2014": "51.3", "stdvhs2014": "10.72"}, {"schid": "170530080262006", "name": "Chatsworth Grade School", "distid": "170530080260000", "dist": "Prairie Central CUSD 8", "city": "Chatsworth", "county": "Livingston", "type": "ELEMENTARY", "lowinc2004": "54.8", "percmin2004": "6.5", "enroll2004": "124", "enrolldist2004": "1889", "grades2004": "PK K 1 2 3 4", "sel2004elem": "Yes", "elemcomp2004": "63.9", "sel2004hs": "No", "hscomp2004": "None", "zelemscore2004": "0.03", "avgelem2004": "63.6", "stdvelem2004": "10.98", "zhsscore2004": "None", "avghs2004": "None", "stdvhs2004": "None", "lowinc2005": "66.7", "percmin2005": "6.8", "enroll2005": "117", "enrolldist2005": "2307", "grades2005": "PK K 1 2 3 4", "sel2005elem": "Yes", "elemcomp2005": "89.1", "sel2005hs": "No", "hscomp2005": "None", "zelemscore2005": "2.20", "avgelem2005": "63.9", "stdvelem2005": "11.47", "zhsscore2005": "None", "avghs2005": "None", "stdvhs2005": "None", "lowinc2006": "66.9", "percmin2006": "2.5", "enroll2006": "121", "enrolldist2006": "2241", "grades2006": "PK K 1 2 3 4", "sel2006elem": "Yes", "elemcomp2006": "94.0", "sel2006hs": "No", "hscomp2006": "None", "zelemscore2006": "2.54", "avgelem2006": "71.7", "stdvelem2006": "8.78", "zhsscore2006": "None", "avghs2006": "None", "stdvhs2006": "None", "lowinc2007": "70.2", "percmin2007": "3.1", "enroll2007": "131", "enrolldist2007": "2199", "grades2007": "PK K 1 2 3 4", "sel2007elem": "Yes", "elemcomp2007": "97.6", "sel2007hs": "No", "hscomp2007": "None", "zelemscore2007": "2.88", "avgelem2007": "68.8", "stdvelem2007": "10.01", "zhsscore2007": "None", "avghs2007": "None", "stdvhs2007": "None", "lowinc2008": "75.9", "percmin2008": "5.1", "enroll2008": "137", "enrolldist2008": "2187", "grades2008": "PK K 1 2 3 4", "sel2008elem": "Yes", "elemcomp2008": "93.5", "sel2008hs": "No", "hscomp2008": "None", "zelemscore2008": "2.42", "avgelem2008": "69.8", "stdvelem2008": "9.82", "zhsscore2008": "None", "avghs2008": "None", "stdvhs2008": "None", "lowinc2009": "65.9", "percmin2009": "5.1", "enroll2009": "138", "enrolldist2009": "2178", "grades2009": "PK K 1 2 3 4", "sel2009elem": "Yes", "elemcomp2009": "93.9", "sel2009hs": "No", "hscomp2009": "None", "zelemscore2009": "2.18", "avgelem2009": "75.5", "stdvelem2009": "8.45", "zhsscore2009": "None", "avghs2009": "None", "stdvhs2009": "None", "lowinc2010": "56.7", "percmin2010": "4.3", "enroll2010": "141", "enrolldist2010": "2110", "grades2010": "PK K 1 2 3 4", "sel2010elem": "Yes", "elemcomp2010": "87.6", "sel2010hs": "No", "hscomp2010": "None", "zelemscore2010": "1.10", "avgelem2010": "80.0", "stdvelem2010": "6.84", "zhsscore2010": "None", "avghs2010": "None", "stdvhs2010": "None", "lowinc2011": "65.9", "percmin2011": "3.0", "enroll2011": "135", "enrolldist2011": "2154", "grades2011": "PK K 1 2 3 4", "sel2011elem": "Yes", "elemcomp2011": "85.3", "sel2011hs": "No", "hscomp2011": "None", "zelemscore2011": "0.87", "avgelem2011": "78.9", "stdvelem2011": "7.34", "zhsscore2011": "None", "avghs2011": "None", "stdvhs2011": "None", "lowinc2012": "69.2", "percmin2012": "11.0", "enroll2012": "146", "enrolldist2012": "2160", "grades2012": "PK K 1 2 3 4", "sel2012elem": "Yes", "elemcomp2012": "80.4", "sel2012hs": "No", "hscomp2012": "None", "zelemscore2012": "0.19", "avgelem2012": "79.1", "stdvelem2012": "7.07", "zhsscore2012": "None", "avghs2012": "None", "stdvhs2012": "None", "lowinc2013": "66.7", "percmin2013": "11.9", "enroll2013": "135", "enrolldist2013": "2117", "grades2013": "PK K 1 2 3 4", "sel2013elem": "Yes", "elemcomp2013": "54.1", "sel2013hs": "No", "hscomp2013": "None", "zelemscore2013": "0.15", "avgelem2013": "52.7", "stdvelem2013": "9.67", "zhsscore2013": "None", "avghs2013": "None", "stdvhs2013": "None", "lowinc2014": "76.8", "percmin2014": "12.3", "enroll2014": "138", "enrolldist2014": "2144", "grades2014": "PK K 1 2 3 4", "sel2014elem": "Yes", "elemcomp2014": "81.3", "sel2014hs": "No", "hscomp2014": "None", "zelemscore2014": "2.92", "avgelem2014": "47.2", "stdvelem2014": "11.66", "zhsscore2014": "None", "avghs2014": "None", "stdvhs2014": "None"}, {"schid": "170530080262007", "name": "Prairie Central Upper Elementary", "distid": "170530080260000", "dist": "Prairie Central CUSD 8", "city": "Forrest", "county": "Livingston", "type": "ELEMENTARY", "lowinc2004": "29.0", "percmin2004": "5.0", "enroll2004": "259", "enrolldist2004": "1889", "grades2004": "5 6", "sel2004elem": "Yes", "elemcomp2004": "79.0", "sel2004hs": "No", "hscomp2004": "None", "zelemscore2004": "0.56", "avgelem2004": "73.9", "stdvelem2004": "9.01", "zhsscore2004": "None", "avghs2004": "None", "stdvhs2004": "None", "lowinc2005": "25.4", "percmin2005": "5.9", "enroll2005": "323", "enrolldist2005": "2307", "grades2005": "5 6", "sel2005elem": "Yes", "elemcomp2005": "81.4", "sel2005hs": "No", "hscomp2005": "None", "zelemscore2005": "0.39", "avgelem2005": "78.3", "stdvelem2005": "8.04", "zhsscore2005": "None", "avghs2005": "None", "stdvhs2005": "None", "lowinc2006": "37.6", "percmin2006": "6.7", "enroll2006": "330", "enrolldist2006": "2241", "grades2006": "5 6", "sel2006elem": "Yes", "elemcomp2006": "84.5", "sel2006hs": "No", "hscomp2006": "None", "zelemscore2006": "0.37", "avgelem2006": "81.9", "stdvelem2006": "7.01", "zhsscore2006": "None", "avghs2006": "None", "stdvhs2006": "None", "lowinc2007": "35.5", "percmin2007": "5.8", "enroll2007": "310", "enrolldist2007": "2199", "grades2007": "5 6", "sel2007elem": "Yes", "elemcomp2007": "89.2", "sel2007hs": "No", "hscomp2007": "None", "zelemscore2007": "0.99", "avgelem2007": "82.9", "stdvelem2007": "6.36", "zhsscore2007": "None", "avghs2007": "None", "stdvhs2007": "None", "lowinc2008": "31.0", "percmin2008": "7.9", "enroll2008": "290", "enrolldist2008": "2187", "grades2008": "5 6", "sel2008elem": "Yes", "elemcomp2008": "92.5", "sel2008hs": "No", "hscomp2008": "None", "zelemscore2008": "1.49", "avgelem2008": "83.5", "stdvelem2008": "6.05", "zhsscore2008": "None", "avghs2008": "None", "stdvhs2008": "None", "lowinc2009": "40.1", "percmin2009": "9.4", "enroll2009": "297", "enrolldist2009": "2178", "grades2009": "5 6", "sel2009elem": "Yes", "elemcomp2009": "95.4", "sel2009hs": "No", "hscomp2009": "None", "zelemscore2009": "2.34", "avgelem2009": "81.5", "stdvelem2009": "5.96", "zhsscore2009": "None", "avghs2009": "None", "stdvhs2009": "None", "lowinc2010": "44.9", "percmin2010": "7.5", "enroll2010": "321", "enrolldist2010": "2110", "grades2010": "5 6", "sel2010elem": "Yes", "elemcomp2010": "94.9", "sel2010hs": "No", "hscomp2010": "None", "zelemscore2010": "1.98", "avgelem2010": "83.0", "stdvelem2010": "6.01", "zhsscore2010": "None", "avghs2010": "None", "stdvhs2010": "None", "lowinc2011": "41.6", "percmin2011": "7.1", "enroll2011": "339", "enrolldist2011": "2154", "grades2011": "5 6", "sel2011elem": "Yes", "elemcomp2011": "95.2", "sel2011hs": "No", "hscomp2011": "None", "zelemscore2011": "2.00", "avgelem2011": "84.6", "stdvelem2011": "5.30", "zhsscore2011": "None", "avghs2011": "None", "stdvhs2011": "None", "lowinc2012": "39.9", "percmin2012": "9.7", "enroll2012": "298", "enrolldist2012": "2160", "grades2012": "5 6", "sel2012elem": "Yes", "elemcomp2012": "97.9", "sel2012hs": "No", "hscomp2012": "None", "zelemscore2012": "2.22", "avgelem2012": "87.4", "stdvelem2012": "4.72", "zhsscore2012": "None", "avghs2012": "None", "stdvhs2012": "None", "lowinc2013": "42.6", "percmin2013": "9.4", "enroll2013": "277", "enrolldist2013": "2117", "grades2013": "5 6", "sel2013elem": "Yes", "elemcomp2013": "80.0", "sel2013hs": "No", "hscomp2013": "None", "zelemscore2013": "2.13", "avgelem2013": "60.5", "stdvelem2013": "9.17", "zhsscore2013": "None", "avghs2013": "None", "stdvhs2013": "None", "lowinc2014": "45.0", "percmin2014": "10.3", "enroll2014": "320", "enrolldist2014": "2144", "grades2014": "5 6", "sel2014elem": "Yes", "elemcomp2014": "69.9", "sel2014hs": "No", "hscomp2014": "None", "zelemscore2014": "0.98", "avgelem2014": "60.5", "stdvelem2014": "9.63", "zhsscore2014": "None", "avghs2014": "None", "stdvhs2014": "None"}, {"schid": "170530080261001", "name": "Prairie Central Jr High School", "distid": "170530080260000", "dist": "Prairie Central CUSD 8", "city": "Forrest", "county": "Livingston", "type": "MIDDLE SCHL", "lowinc2004": "26.2", "percmin2004": "7.7", "enroll2004": "313", "enrolldist2004": "1889", "grades2004": "7 8", "sel2004elem": "Yes", "elemcomp2004": "77.5", "sel2004hs": "No", "hscomp2004": "None", "zelemscore2004": "0.40", "avgelem2004": "73.9", "stdvelem2004": "9.01", "zhsscore2004": "None", "avghs2004": "None", "stdvhs2004": "None", "lowinc2005": "34.1", "percmin2005": "6.0", "enroll2005": "364", "enrolldist2005": "2307", "grades2005": "7 8", "sel2005elem": "Yes", "elemcomp2005": "75.6", "sel2005hs": "No", "hscomp2005": "None", "zelemscore2005": "0.06", "avgelem2005": "75.1", "stdvelem2005": "8.39", "zhsscore2005": "None", "avghs2005": "None", "stdvhs2005": "None", "lowinc2006": "34.3", "percmin2006": "4.2", "enroll2006": "335", "enrolldist2006": "2241", "grades2006": "7 8", "sel2006elem": "Yes", "elemcomp2006": "85.8", "sel2006hs": "No", "hscomp2006": "None", "zelemscore2006": "0.56", "avgelem2006": "81.9", "stdvelem2006": "7.01", "zhsscore2006": "None", "avghs2006": "None", "stdvhs2006": "None", "lowinc2007": "35.2", "percmin2007": "5.6", "enroll2007": "321", "enrolldist2007": "2199", "grades2007": "7 8", "sel2007elem": "Yes", "elemcomp2007": "84.9", "sel2007hs": "No", "hscomp2007": "None", "zelemscore2007": "0.31", "avgelem2007": "82.9", "stdvelem2007": "6.36", "zhsscore2007": "None", "avghs2007": "None", "stdvhs2007": "None", "lowinc2008": "36.1", "percmin2008": "5.2", "enroll2008": "327", "enrolldist2008": "2187", "grades2008": "7 8", "sel2008elem": "Yes", "elemcomp2008": "87.4", "sel2008hs": "No", "hscomp2008": "None", "zelemscore2008": "0.65", "avgelem2008": "83.5", "stdvelem2008": "6.05", "zhsscore2008": "None", "avghs2008": "None", "stdvhs2008": "None", "lowinc2009": "33.3", "percmin2009": "6.5", "enroll2009": "321", "enrolldist2009": "2178", "grades2009": "7 8", "sel2009elem": "Yes", "elemcomp2009": "88.5", "sel2009hs": "No", "hscomp2009": "None", "zelemscore2009": "0.64", "avgelem2009": "84.7", "stdvelem2009": "5.88", "zhsscore2009": "None", "avghs2009": "None", "stdvhs2009": "None", "lowinc2010": "36.1", "percmin2010": "8.2", "enroll2010": "291", "enrolldist2010": "2110", "grades2010": "7 8", "sel2010elem": "Yes", "elemcomp2010": "90.0", "sel2010hs": "No", "hscomp2010": "None", "zelemscore2010": "0.81", "avgelem2010": "85.7", "stdvelem2010": "5.26", "zhsscore2010": "None", "avghs2010": "None", "stdvhs2010": "None", "lowinc2011": "38.5", "percmin2011": "10.1", "enroll2011": "296", "enrolldist2011": "2154", "grades2011": "7 8", "sel2011elem": "Yes", "elemcomp2011": "90.4", "sel2011hs": "No", "hscomp2011": "None", "zelemscore2011": "0.64", "avgelem2011": "87.3", "stdvelem2011": "4.91", "zhsscore2011": "None", "avghs2011": "None", "stdvhs2011": "None", "lowinc2012": "42.4", "percmin2012": "7.9", "enroll2012": "330", "enrolldist2012": "2160", "grades2012": "7 8", "sel2012elem": "Yes", "elemcomp2012": "89.8", "sel2012hs": "No", "hscomp2012": "None", "zelemscore2012": "0.97", "avgelem2012": "84.8", "stdvelem2012": "5.13", "zhsscore2012": "None", "avghs2012": "None", "stdvhs2012": "None", "lowinc2013": "41.2", "percmin2013": "7.8", "enroll2013": "335", "enrolldist2013": "2117", "grades2013": "7 8", "sel2013elem": "Yes", "elemcomp2013": "63.9", "sel2013hs": "No", "hscomp2013": "None", "zelemscore2013": "0.37", "avgelem2013": "60.5", "stdvelem2013": "9.17", "zhsscore2013": "None", "avghs2013": "None", "stdvhs2013": "None", "lowinc2014": "43.7", "percmin2014": "10.4", "enroll2014": "309", "enrolldist2014": "2144", "grades2014": "7 8", "sel2014elem": "Yes", "elemcomp2014": "71.4", "sel2014hs": "No", "hscomp2014": "None", "zelemscore2014": "1.13", "avgelem2014": "60.5", "stdvelem2014": "9.63", "zhsscore2014": "None", "avghs2014": "None", "stdvhs2014": "None"}, {"schid": "170530080262002", "name": "Meadowbrook Elem School", "distid": "170530080260000", "dist": "Prairie Central CUSD 8", "city": "Forrest", "county": "Livingston", "type": "ELEMENTARY", "lowinc2004": "26.8", "percmin2004": "3.1", "enroll2004": "194", "enrolldist2004": "1889", "grades2004": "PK K 1 2 3 4", "sel2004elem": "Yes", "elemcomp2004": "87.0", "sel2004hs": "No", "hscomp2004": "None", "zelemscore2004": "1.45", "avgelem2004": "73.9", "stdvelem2004": "9.01", "zhsscore2004": "None", "avghs2004": "None", "stdvhs2004": "None", "lowinc2005": "29.0", "percmin2005": "2.1", "enroll2005": "193", "enrolldist2005": "2307", "grades2005": "K 1 2 3 4", "sel2005elem": "Yes", "elemcomp2005": "83.9", "sel2005hs": "No", "hscomp2005": "None", "zelemscore2005": "0.70", "avgelem2005": "78.3", "stdvelem2005": "8.04", "zhsscore2005": "None", "avghs2005": "None", "stdvhs2005": "None", "lowinc2006": "33.9", "percmin2006": "4.4", "enroll2006": "180", "enrolldist2006": "2241", "grades2006": "K 1 2 3 4", "sel2006elem": "Yes", "elemcomp2006": "91.4", "sel2006hs": "No", "hscomp2006": "None", "zelemscore2006": "1.36", "avgelem2006": "81.9", "stdvelem2006": "7.01", "zhsscore2006": "None", "avghs2006": "None", "stdvhs2006": "None", "lowinc2007": "37.3", "percmin2007": "4.5", "enroll2007": "177", "enrolldist2007": "2199", "grades2007": "K 1 2 3 4", "sel2007elem": "Yes", "elemcomp2007": "98.3", "sel2007hs": "No", "hscomp2007": "None", "zelemscore2007": "2.42", "avgelem2007": "82.9", "stdvelem2007": "6.36", "zhsscore2007": "None", "avghs2007": "None", "stdvhs2007": "None", "lowinc2008": "32.4", "percmin2008": "6.9", "enroll2008": "173", "enrolldist2008": "2187", "grades2008": "K 1 2 3 4", "sel2008elem": "Yes", "elemcomp2008": "96.3", "sel2008hs": "No", "hscomp2008": "None", "zelemscore2008": "2.12", "avgelem2008": "83.5", "stdvelem2008": "6.05", "zhsscore2008": "None", "avghs2008": "None", "stdvhs2008": "None", "lowinc2009": "31.5", "percmin2009": "8.4", "enroll2009": "178", "enrolldist2009": "2178", "grades2009": "PK K 1 2 3 4", "sel2009elem": "Yes", "elemcomp2009": "95.8", "sel2009hs": "No", "hscomp2009": "None", "zelemscore2009": "1.88", "avgelem2009": "84.7", "stdvelem2009": "5.88", "zhsscore2009": "None", "avghs2009": "None", "stdvhs2009": "None", "lowinc2010": "33.5", "percmin2010": "7.6", "enroll2010": "170", "enrolldist2010": "2110", "grades2010": "PK K 1 2 3 4", "sel2010elem": "Yes", "elemcomp2010": "96.8", "sel2010hs": "No", "hscomp2010": "None", "zelemscore2010": "2.10", "avgelem2010": "85.7", "stdvelem2010": "5.26", "zhsscore2010": "None", "avghs2010": "None", "stdvhs2010": "None", "lowinc2011": "40.1", "percmin2011": "9.6", "enroll2011": "187", "enrolldist2011": "2154", "grades2011": "PK K 1 2 3 4", "sel2011elem": "Yes", "elemcomp2011": "95.1", "sel2011hs": "No", "hscomp2011": "None", "zelemscore2011": "1.98", "avgelem2011": "84.6", "stdvelem2011": "5.30", "zhsscore2011": "None", "avghs2011": "None", "stdvhs2011": "None", "lowinc2012": "39.9", "percmin2012": "10.6", "enroll2012": "198", "enrolldist2012": "2160", "grades2012": "PK K 1 2 3 4", "sel2012elem": "Yes", "elemcomp2012": "92.9", "sel2012hs": "No", "hscomp2012": "None", "zelemscore2012": "1.17", "avgelem2012": "87.4", "stdvelem2012": "4.72", "zhsscore2012": "None", "avghs2012": "None", "stdvhs2012": "None", "lowinc2013": "42.8", "percmin2013": "12.2", "enroll2013": "180", "enrolldist2013": "2117", "grades2013": "PK K 1 2 3 4", "sel2013elem": "Yes", "elemcomp2013": "64.5", "sel2013hs": "No", "hscomp2013": "None", "zelemscore2013": "0.44", "avgelem2013": "60.5", "stdvelem2013": "9.17", "zhsscore2013": "None", "avghs2013": "None", "stdvhs2013": "None", "lowinc2014": "45.9", "percmin2014": "13.4", "enroll2014": "172", "enrolldist2014": "2144", "grades2014": "PK K 1 2 3 4", "sel2014elem": "Yes", "elemcomp2014": "43.8", "sel2014hs": "No", "hscomp2014": "None", "zelemscore2014": "-1.73", "avgelem2014": "60.5", "stdvelem2014": "9.63", "zhsscore2014": "None", "avghs2014": "None", "stdvhs2014": "None"}, {"schid": "170530080262001", "name": "Chenoa Elem School", "distid": "170530080260000", "dist": "Prairie Central CUSD 8", "city": "Chenoa", "county": "Livingston", "type": "ELEMENTARY", "lowinc2004": "35.7", "percmin2004": "6.6", "enroll2004": "333", "enrolldist2004": "466", "grades2004": "PK K 1 2 3 4 5 6 7 8", "sel2004elem": "Yes", "elemcomp2004": "64.4", "sel2004hs": "No", "hscomp2004": "None", "zelemscore2004": "-0.71", "avgelem2004": "70.8", "stdvelem2004": "9.01", "zhsscore2004": "None", "avghs2004": "None", "stdvhs2004": "None", "lowinc2005": "36.0", "percmin2005": "5.6", "enroll2005": "178", "enrolldist2005": "2307", "grades2005": "PK K 1 2 3 4", "sel2005elem": "Yes", "elemcomp2005": "83.1", "sel2005hs": "No", "hscomp2005": "None", "zelemscore2005": "0.95", "avgelem2005": "75.1", "stdvelem2005": "8.39", "zhsscore2005": "None", "avghs2005": "None", "stdvhs2005": "None", "lowinc2006": "45.4", "percmin2006": "8.0", "enroll2006": "174", "enrolldist2006": "2241", "grades2006": "PK K 1 2 3 4", "sel2006elem": "Yes", "elemcomp2006": "86.0", "sel2006hs": "No", "hscomp2006": "None", "zelemscore2006": "0.97", "avgelem2006": "79.4", "stdvelem2006": "6.77", "zhsscore2006": "None", "avghs2006": "None", "stdvhs2006": "None", "lowinc2007": "54.1", "percmin2007": "6.5", "enroll2007": "170", "enrolldist2007": "2199", "grades2007": "PK K 1 2 3 4", "sel2007elem": "Yes", "elemcomp2007": "90.4", "sel2007hs": "No", "hscomp2007": "None", "zelemscore2007": "1.73", "avgelem2007": "78.0", "stdvelem2007": "7.17", "zhsscore2007": "None", "avghs2007": "None", "stdvhs2007": "None", "lowinc2008": "35.4", "percmin2008": "3.4", "enroll2008": "178", "enrolldist2008": "2187", "grades2008": "PK K 1 2 3 4", "sel2008elem": "Yes", "elemcomp2008": "92.9", "sel2008hs": "No", "hscomp2008": "None", "zelemscore2008": "1.56", "avgelem2008": "83.5", "stdvelem2008": "6.05", "zhsscore2008": "None", "avghs2008": "None", "stdvhs2008": "None", "lowinc2009": "41.2", "percmin2009": "4.0", "enroll2009": "177", "enrolldist2009": "2178", "grades2009": "PK K 1 2 3 4", "sel2009elem": "Yes", "elemcomp2009": "91.2", "sel2009hs": "No", "hscomp2009": "None", "zelemscore2009": "1.64", "avgelem2009": "81.5", "stdvelem2009": "5.96", "zhsscore2009": "None", "avghs2009": "None", "stdvhs2009": "None", "lowinc2010": "43.2", "percmin2010": "4.1", "enroll2010": "169", "enrolldist2010": "2110", "grades2010": "PK K 1 2 3 4", "sel2010elem": "Yes", "elemcomp2010": "92.1", "sel2010hs": "No", "hscomp2010": "None", "zelemscore2010": "1.51", "avgelem2010": "83.0", "stdvelem2010": "6.01", "zhsscore2010": "None", "avghs2010": "None", "stdvhs2010": "None", "lowinc2011": "40.7", "percmin2011": "6.8", "enroll2011": "177", "enrolldist2011": "2154", "grades2011": "PK K 1 2 3 4", "sel2011elem": "Yes", "elemcomp2011": "99.2", "sel2011hs": "No", "hscomp2011": "None", "zelemscore2011": "2.75", "avgelem2011": "84.6", "stdvelem2011": "5.30", "zhsscore2011": "None", "avghs2011": "None", "stdvhs2011": "None", "lowinc2012": "45.8", "percmin2012": "8.5", "enroll2012": "177", "enrolldist2012": "2160", "grades2012": "PK K 1 2 3 4", "sel2012elem": "Yes", "elemcomp2012": "95.5", "sel2012hs": "No", "hscomp2012": "None", "zelemscore2012": "2.08", "avgelem2012": "84.8", "stdvelem2012": "5.13", "zhsscore2012": "None", "avghs2012": "None", "stdvhs2012": "None", "lowinc2013": "58.5", "percmin2013": "8.7", "enroll2013": "183", "enrolldist2013": "2117", "grades2013": "PK K 1 2 3 4", "sel2013elem": "Yes", "elemcomp2013": "74.6", "sel2013hs": "No", "hscomp2013": "None", "zelemscore2013": "1.76", "avgelem2013": "56.8", "stdvelem2013": "10.08", "zhsscore2013": "None", "avghs2013": "None", "stdvhs2013": "None", "lowinc2014": "62.1", "percmin2014": "10.3", "enroll2014": "174", "enrolldist2014": "2144", "grades2014": "PK K 1 2 3 4", "sel2014elem": "Yes", "elemcomp2014": "57.0", "sel2014hs": "No", "hscomp2014": "None", "zelemscore2014": "0.47", "avgelem2014": "52.0", "stdvelem2014": "10.74", "zhsscore2014": "None", "avghs2014": "None", "stdvhs2014": "None"}, {"schid": "170530080262005", "name": "Westview Elem School", "distid": "170530080260000", "dist": "Prairie Central CUSD 8", "city": "Fairbury", "county": "Livingston", "type": "ELEMENTARY", "lowinc2004": "24.9", "percmin2004": "12.4", "enroll2004": "394", "enrolldist2004": "1889", "grades2004": "PK K 1 2 3 4", "sel2004elem": "Yes", "elemcomp2004": "77.6", "sel2004hs": "No", "hscomp2004": "None", "zelemscore2004": "0.41", "avgelem2004": "73.9", "stdvelem2004": "9.01", "zhsscore2004": "None", "avghs2004": "None", "stdvhs2004": "None", "lowinc2005": "31.5", "percmin2005": "13.9", "enroll2005": "410", "enrolldist2005": "2307", "grades2005": "PK K 1 2 3 4", "sel2005elem": "Yes", "elemcomp2005": "92.5", "sel2005hs": "No", "hscomp2005": "None", "zelemscore2005": "2.07", "avgelem2005": "75.1", "stdvelem2005": "8.39", "zhsscore2005": "None", "avghs2005": "None", "stdvhs2005": "None", "lowinc2006": "30.1", "percmin2006": "13.2", "enroll2006": "402", "enrolldist2006": "2241", "grades2006": "PK K 1 2 3 4", "sel2006elem": "Yes", "elemcomp2006": "91.2", "sel2006hs": "No", "hscomp2006": "None", "zelemscore2006": "1.33", "avgelem2006": "81.9", "stdvelem2006": "7.01", "zhsscore2006": "None", "avghs2006": "None", "stdvhs2006": "None", "lowinc2007": "32.3", "percmin2007": "11.8", "enroll2007": "399", "enrolldist2007": "2199", "grades2007": "PK K 1 2 3 4", "sel2007elem": "Yes", "elemcomp2007": "94.8", "sel2007hs": "No", "hscomp2007": "None", "zelemscore2007": "1.87", "avgelem2007": "82.9", "stdvelem2007": "6.36", "zhsscore2007": "None", "avghs2007": "None", "stdvhs2007": "None", "lowinc2008": "30.7", "percmin2008": "10.2", "enroll2008": "423", "enrolldist2008": "2187", "grades2008": "PK K 1 2 3 4", "sel2008elem": "Yes", "elemcomp2008": "89.9", "sel2008hs": "No", "hscomp2008": "None", "zelemscore2008": "1.06", "avgelem2008": "83.5", "stdvelem2008": "6.05", "zhsscore2008": "None", "avghs2008": "None", "stdvhs2008": "None", "lowinc2009": "26.6", "percmin2009": "9.3", "enroll2009": "418", "enrolldist2009": "2178", "grades2009": "PK K 1 2 3 4", "sel2009elem": "Yes", "elemcomp2009": "88.8", "sel2009hs": "No", "hscomp2009": "None", "zelemscore2009": "0.40", "avgelem2009": "86.8", "stdvelem2009": "5.14", "zhsscore2009": "None", "avghs2009": "None", "stdvhs2009": "None", "lowinc2010": "31.0", "percmin2010": "10.0", "enroll2010": "400", "enrolldist2010": "2110", "grades2010": "PK K 1 2 3 4", "sel2010elem": "Yes", "elemcomp2010": "88.1", "sel2010hs": "No", "hscomp2010": "None", "zelemscore2010": "0.45", "avgelem2010": "85.7", "stdvelem2010": "5.26", "zhsscore2010": "None", "avghs2010": "None", "stdvhs2010": "None", "lowinc2011": "30.3", "percmin2011": "8.2", "enroll2011": "379", "enrolldist2011": "2154", "grades2011": "PK K 1 2 3 4", "sel2011elem": "Yes", "elemcomp2011": "93.5", "sel2011hs": "No", "hscomp2011": "None", "zelemscore2011": "1.27", "avgelem2011": "87.3", "stdvelem2011": "4.91", "zhsscore2011": "None", "avghs2011": "None", "stdvhs2011": "None", "lowinc2012": "33.0", "percmin2012": "7.3", "enroll2012": "397", "enrolldist2012": "2160", "grades2012": "PK K 1 2 3 4", "sel2012elem": "Yes", "elemcomp2012": "93.1", "sel2012hs": "No", "hscomp2012": "None", "zelemscore2012": "1.21", "avgelem2012": "87.4", "stdvelem2012": "4.72", "zhsscore2012": "None", "avghs2012": "None", "stdvhs2012": "None", "lowinc2013": "38.0", "percmin2013": "6.1", "enroll2013": "395", "enrolldist2013": "2117", "grades2013": "PK K 1 2 3 4", "sel2013elem": "Yes", "elemcomp2013": "65.2", "sel2013hs": "No", "hscomp2013": "None", "zelemscore2013": "-0.10", "avgelem2013": "66.1", "stdvelem2013": "8.82", "zhsscore2013": "None", "avghs2013": "None", "stdvhs2013": "None", "lowinc2014": "42.4", "percmin2014": "11.0", "enroll2014": "408", "enrolldist2014": "2144", "grades2014": "PK K 1 2 3 4", "sel2014elem": "Yes", "elemcomp2014": "50.4", "sel2014hs": "No", "hscomp2014": "None", "zelemscore2014": "-1.05", "avgelem2014": "60.5", "stdvelem2014": "9.63", "zhsscore2014": "None", "avghs2014": "None", "stdvhs2014": "None"}]