[{"schid": "350501400170001", "name": "Ottawa Township High School", "distid": "350501400170000", "dist": "Ottawa Twp HSD 140", "city": "Ottawa", "county": "La Salle", "type": "HIGH SCHOOL", "lowinc2004": "8.1", "percmin2004": "5.6", "enroll2004": "1576", "enrolldist2004": "1576", "grades2004": "9 10 11 12", "sel2004elem": "No", "elemcomp2004": "None", "sel2004hs": "Yes", "hscomp2004": "51.5", "zelemscore2004": "None", "avgelem2004": "None", "stdvelem2004": "None", "zhsscore2004": "-1.29", "avghs2004": "64.5", "stdvhs2004": "10.10", "lowinc2005": "12.2", "percmin2005": "6.7", "enroll2005": "1617", "enrolldist2005": "1617", "grades2005": "9 10 11 12", "sel2005elem": "No", "elemcomp2005": "None", "sel2005hs": "Yes", "hscomp2005": "48.6", "zelemscore2005": "None", "avgelem2005": "None", "stdvelem2005": "None", "zhsscore2005": "-1.75", "avghs2005": "64.9", "stdvhs2005": "9.32", "lowinc2006": "12.0", "percmin2006": "7.7", "enroll2006": "1646", "enrolldist2006": "1646", "grades2006": "9 10 11 12", "sel2006elem": "No", "elemcomp2006": "None", "sel2006hs": "Yes", "hscomp2006": "51.5", "zelemscore2006": "None", "avgelem2006": "None", "stdvelem2006": "None", "zhsscore2006": "-1.41", "avghs2006": "64.9", "stdvhs2006": "9.47", "lowinc2007": "13.2", "percmin2007": "8.5", "enroll2007": "1661", "enrolldist2007": "1661", "grades2007": "9 10 11 12", "sel2007elem": "No", "elemcomp2007": "None", "sel2007hs": "Yes", "hscomp2007": "51.6", "zelemscore2007": "None", "avgelem2007": "None", "stdvelem2007": "None", "zhsscore2007": "-0.30", "avghs2007": "54.3", "stdvhs2007": "9.04", "lowinc2008": "14.8", "percmin2008": "8.8", "enroll2008": "1576", "enrolldist2008": "1576", "grades2008": "9 10 11 12", "sel2008elem": "No", "elemcomp2008": "None", "sel2008hs": "Yes", "hscomp2008": "55.6", "zelemscore2008": "None", "avgelem2008": "None", "stdvelem2008": "None", "zhsscore2008": "-0.03", "avghs2008": "55.8", "stdvhs2008": "8.80", "lowinc2009": "16.6", "percmin2009": "10.8", "enroll2009": "1562", "enrolldist2009": "1562", "grades2009": "9 10 11 12", "sel2009elem": "No", "elemcomp2009": "None", "sel2009hs": "Yes", "hscomp2009": "52.3", "zelemscore2009": "None", "avgelem2009": "None", "stdvelem2009": "None", "zhsscore2009": "-0.63", "avghs2009": "57.7", "stdvhs2009": "8.64", "lowinc2010": "22.9", "percmin2010": "11.5", "enroll2010": "1451", "enrolldist2010": "1451", "grades2010": "9 10 11 12", "sel2010elem": "No", "elemcomp2010": "None", "sel2010hs": "Yes", "hscomp2010": "55.6", "zelemscore2010": "None", "avgelem2010": "None", "stdvelem2010": "None", "zhsscore2010": "-0.41", "avghs2010": "59.1", "stdvhs2010": "8.51", "lowinc2011": "25.9", "percmin2011": "13.7", "enroll2011": "1440", "enrolldist2011": "1440", "grades2011": "9 10 11 12", "sel2011elem": "No", "elemcomp2011": "None", "sel2011hs": "Yes", "hscomp2011": "48.9", "zelemscore2011": "None", "avgelem2011": "None", "stdvelem2011": "None", "zhsscore2011": "-0.44", "avghs2011": "53.4", "stdvhs2011": "10.18", "lowinc2012": "27.7", "percmin2012": "15.2", "enroll2012": "1440", "enrolldist2012": "1440", "grades2012": "9 10 11 12", "sel2012elem": "No", "elemcomp2012": "None", "sel2012hs": "Yes", "hscomp2012": "47.9", "zelemscore2012": "None", "avgelem2012": "None", "stdvelem2012": "None", "zhsscore2012": "-0.58", "avghs2012": "54.0", "stdvhs2012": "10.53", "lowinc2013": "31.2", "percmin2013": "15.9", "enroll2013": "1476", "enrolldist2013": "1476", "grades2013": "9 10 11 12", "sel2013elem": "No", "elemcomp2013": "None", "sel2013hs": "Yes", "hscomp2013": "51.6", "zelemscore2013": "None", "avgelem2013": "None", "stdvelem2013": "None", "zhsscore2013": "-0.49", "avghs2013": "56.7", "stdvhs2013": "10.30", "lowinc2014": "31.8", "percmin2014": "14.7", "enroll2014": "1445", "enrolldist2014": "1445", "grades2014": "9 10 11 12", "sel2014elem": "No", "elemcomp2014": "None", "sel2014hs": "Yes", "hscomp2014": "57.0", "zelemscore2014": "None", "avgelem2014": "None", "stdvelem2014": "None", "zhsscore2014": "-0.13", "avghs2014": "58.2", "stdvhs2014": "9.56"}]